j2yaml/__init__.py
j2yaml/main.py
j2yaml/test.py
j2yaml-0.1.1.dist-info/LICENSE
j2yaml-0.1.1.dist-info/METADATA
j2yaml-0.1.1.dist-info/WHEEL
j2yaml-0.1.1.dist-info/top_level.txt
j2yaml-0.1.1.dist-info/RECORD
