Metadata-Version: 2.1
Name: j2yaml
Version: 0.1.1
Summary: Jinja2-templates inside YAML-files.
Home-page: https://github.com/tombayo/j2yaml
Author: tombayo
Author-email: pypi@tombayo.com
License: GPLv3
Classifier: Programming Language :: Python
Classifier: Programming Language :: Python :: 3.8
Requires-Python: >=3.8
License-File: LICENSE
Requires-Dist: Jinja2 ==3.1.3
Requires-Dist: MarkupSafe ==2.1.5
Requires-Dist: PyYAML ==6.0.1
Provides-Extra: dev
Requires-Dist: pytest >=7.0 ; extra == 'dev'
Requires-Dist: twine >=4.0.2 ; extra == 'dev'
